{
  "id": "bracket-sequences-ii-prefix-count",
  "title": "Bracket Sequences II",
  "difficulty": "intermediate",
  "tags": [
    "math"
  ],
  "estimatedMinutes": 75,
  "language": "python",
  "description": "Your task is to calculate the number of valid bracket sequences of length n when a prefix of the sequence is given.\n\nInput:\n- First line: integer n\n- Second line: string s (the prefix)\n\nA valid bracket sequence uses '(' and ')', never has a prefix with more ')' than '(', and ends with equal numbers of '(' and ')'.\n\nOutput: Print the number of sequences modulo 10^9+7.",
  "examples": [
    {
      "input": "6\n(()",
      "output": "2",
      "explanation": "Prefix balances as 1,2,1. Remaining length m=3, current balance b=1. Possible valid completions are: ()) and )()."
    }
  ],
  "constraints": [
    "1 ≤ k ≤ n ≤ 10^6",
    "Prefix consists of '(' and ')'",
    "Modulo 1,000,000,007"
  ],
  "mcqChain": [
    {
      "id": "q1",
      "phase": "Understanding the Problem",
      "questionText": "Scan the prefix \"(()\" from left to right. What are the running balances after each character?\nBalance: add +1 for '(', -1 for ')'.",
      "diagram": "chars:  (   (   )\nbal:    ?   ?   ?",
      "options": [
        {
          "label": "1, 2, 1",
          "isCode": false
        },
        {
          "label": "1, 0, -1",
          "isCode": false
        },
        {
          "label": "0, 1, 0",
          "isCode": false
        },
        {
          "label": "1, 1, 2",
          "isCode": false
        }
      ],
      "correctIndex": 0,
      "explanation": "Each '(' adds 1, each ')' subtracts 1: 1 → 2 → 1. The balance never goes below 0 here.",
      "wrongExplanations": {
        "1": "This would mean subtracting at the second '(', which is wrong.",
        "2": "This starts at 0 after reading '(', which ignores the first +1.",
        "3": "This keeps balance constant at the second '(', which is incorrect."
      },
      "hint": "Start at 0. Apply +1 for '(', then +1, then -1.",
      "isCodeBuilding": false,
      "codeSnippet": null,
      "codeLabel": null
    },
    {
      "id": "q2",
      "phase": "Understanding the Problem",
      "questionText": "For n=4 and prefix \")(\", can any valid full sequence of length 4 start with this prefix?",
      "diagram": "prefix: )(\nstep1 balance: -1 → already negative",
      "options": [
        {
          "label": "No, the count is 0",
          "isCode": false
        },
        {
          "label": "Yes, exactly 1",
          "isCode": false
        },
        {
          "label": "Yes, exactly 2",
          "isCode": false
        },
        {
          "label": "Yes, more than 2",
          "isCode": false
        }
      ],
      "correctIndex": 0,
      "explanation": "A valid bracket sequence can never have a negative running balance. The prefix goes negative immediately, so 0.",
      "wrongExplanations": {
        "1": "Even if the final balance can be fixed later, the early negative invalidates the entire sequence.",
        "2": "There is no way to repair a negative prefix.",
        "3": "Invalidity happens at the prefix, regardless of future choices."
      },
      "hint": "Track balance after the first character ')'.",
      "isCodeBuilding": false,
      "codeSnippet": null,
      "codeLabel": null
    },
    {
      "id": "q3",
      "phase": "Understanding the Problem",
      "questionText": "If n=6 and the prefix is \"((\", what is the number of remaining positions m to fill?",
      "diagram": "n=6, k=len(\"((\")=2",
      "options": [
        {
          "label": "m = 4",
          "isCode": false
        },
        {
          "label": "m = 2",
          "isCode": false
        },
        {
          "label": "m = 3",
          "isCode": false
        },
        {
          "label": "m depends on balance, not k",
          "isCode": false
        }
      ],
      "correctIndex": 0,
      "explanation": "Remaining positions m = n - k = 6 - 2 = 4.",
      "wrongExplanations": {
        "1": "m is not the current balance; it is total remaining slots.",
        "3": "m is fixed by length difference, independent of balance."
      },
      "hint": "m is the number of characters not in the prefix.",
      "isCodeBuilding": false,
      "codeSnippet": null,
      "codeLabel": null
    },
    {
      "id": "q4",
      "phase": "Understanding the Problem",
      "questionText": "For n=5 and prefix \"(((\", can it be completed to a valid sequence?",
      "diagram": "k=3, m=2, current balance b=3",
      "options": [
        {
          "label": "No, impossible (0 ways)",
          "isCode": false
        },
        {
          "label": "Yes, exactly 1 way",
          "isCode": false
        },
        {
          "label": "Yes, exactly 2 ways",
          "isCode": false
        },
        {
          "label": "It depends only on parity, not on m<b",
          "isCode": false
        }
      ],
      "correctIndex": 0,
      "explanation": "The suffix must reduce balance by b using ')'. With m=2 but b=3, not enough steps to close: impossible.",
      "wrongExplanations": {
        "1": "Even the best choice of two ')' can only reduce balance by 2.",
        "3": "Parity is necessary but not sufficient; m must be ≥ b."
      },
      "hint": "Each ')' reduces balance by 1. Can 2 steps reduce 3?",
      "isCodeBuilding": false,
      "codeSnippet": null,
      "codeLabel": null
    },
    {
      "id": "q5",
      "phase": "Understanding the Problem",
      "questionText": "Which property must the given prefix satisfy to be extendable to a valid sequence?",
      "diagram": null,
      "options": [
        {
          "label": "No prefix should ever make the balance negative",
          "isCode": false
        },
        {
          "label": "The final balance after the prefix is 0",
          "isCode": false
        },
        {
          "label": "The final balance after the prefix is ≤ n/2",
          "isCode": false
        },
        {
          "label": "It ends with '('",
          "isCode": false
        }
      ],
      "correctIndex": 0,
      "explanation": "A valid bracket sequence never has a negative running balance at any prefix.",
      "wrongExplanations": {
        "1": "The prefix can have positive balance; it need not be 0 before completion.",
        "2": "This bound is not the right criterion; remaining length and parity matter.",
        "3": "The last character of the prefix is irrelevant to validity."
      },
      "hint": "Think about when a bracket sequence first becomes invalid.",
      "isCodeBuilding": false,
      "codeSnippet": null,
      "codeLabel": null
    },
    {
      "id": "q6",
      "phase": "Exploring Approaches",
      "questionText": "Let b be the current balance after the prefix and m the remaining length. How many '(' and ')' must appear in the suffix to finish at balance 0?",
      "diagram": "Let x=#'(', y=#')' in suffix, starting from balance b, end at 0.",
      "options": [
        {
          "label": "x = (m - b)/2, y = (m + b)/2",
          "isCode": false
        },
        {
          "label": "x = (m + b)/2, y = (m - b)/2",
          "isCode": false
        },
        {
          "label": "x = m - b, y = b",
          "isCode": false
        },
        {
          "label": "x = b, y = m - b",
          "isCode": false
        }
      ],
      "correctIndex": 0,
      "explanation": "We need x - y = -b and x + y = m. Solving gives x=(m-b)/2 and y=(m+b)/2.",
      "wrongExplanations": {
        "1": "This would make x - y = b, ending above 0.",
        "2": "These don't satisfy x + y = m unless b=0.",
        "3": "These are not tied to the net change needed."
      },
      "hint": "Solve the system: x+y=m and x−y=−b.",
      "isCodeBuilding": false,
      "codeSnippet": null,
      "codeLabel": null
    },
    {
      "id": "q7",
      "phase": "Exploring Approaches",
      "questionText": "When do integer nonnegative x and y exist for the suffix?",
      "diagram": null,
      "options": [
        {
          "label": "(m - b) is even and m ≥ b",
          "isCode": false
        },
        {
          "label": "(m + b) is even and m ≥ b",
          "isCode": false
        },
        {
          "label": "(m - b) is odd and m ≤ b",
          "isCode": false
        },
        {
          "label": "Only need m ≥ b; parity doesn't matter",
          "isCode": false
        }
      ],
      "correctIndex": 1,
      "explanation": "x=(m-b)/2 and y=(m+b)/2 require (m±b) even; also x≥0 ⇒ m≥b.",
      "wrongExplanations": {
        "0": "Parity must apply to both x and y; (m+b) must be even too.",
        "2": "This makes x non-integer or negative.",
        "3": "Parity matters for integer counts."
      },
      "hint": "Check integrality of both x and y and nonnegativity of x.",
      "isCodeBuilding": false,
      "codeSnippet": null,
      "codeLabel": null
    },
    {
      "id": "q8",
      "phase": "Exploring Approaches",
      "questionText": "Ignoring the \"never below 0\" rule, how many suffixes exist by choosing the positions of ')'?",
      "diagram": "Choose y positions for ')', the rest will be '('.",
      "options": [
        {
          "label": "C(m, y)",
          "isCode": false
        },
        {
          "label": "C(m, y+1)",
          "isCode": false
        },
        {
          "label": "C(m, x-1)",
          "isCode": false
        },
        {
          "label": "C(m, m-y-1)",
          "isCode": false
        }
      ],
      "correctIndex": 0,
      "explanation": "There are C(m, y) ways to place y closing brackets among m positions. (Equivalently C(m, x) for '('.)",
      "wrongExplanations": {
        "1": "y+1 closings would overshoot the needed net change.",
        "2": "This undercounts and uses the wrong parameter.",
        "3": "m−y−1 does not correspond to x or y."
      },
      "hint": "Decide which positions are ')'.",
      "isCodeBuilding": false,
      "codeSnippet": null,
      "codeLabel": null
    },
    {
      "id": "q9",
      "phase": "Exploring Approaches",
      "questionText": "For b=1 and m=3, enumerate the 3 unconstrained suffixes (by '(' position). How many of them go below 0 at some point?",
      "diagram": "Suffixes by '(' pos: 1:\"() )\" → ( ) ) ; 2:\") ( )\" ; 3:\") ) (\".\nStart balance b=1 and track.",
      "options": [
        {
          "label": "0",
          "isCode": false
        },
        {
          "label": "1",
          "isCode": false
        },
        {
          "label": "2",
          "isCode": false
        },
        {
          "label": "3",
          "isCode": false
        }
      ],
      "correctIndex": 1,
      "explanation": "Only \") ) (\" dips to -1 on the second step; the other two never go below 0.",
      "wrongExplanations": {
        "0": "One sequence violates the nonnegative rule.",
        "2": "Only one case crosses below; check each prefix carefully."
      },
      "hint": "Track running balance for each candidate.",
      "isCodeBuilding": false,
      "codeSnippet": null,
      "codeLabel": null
    },
    {
      "id": "q10",
      "phase": "Building the Idea",
      "questionText": "Generalizing the previous observation, which binomial term counts the number of \"bad\" suffixes that at some point go below 0?",
      "diagram": null,
      "options": [
        {
          "label": "C(m, y+1)",
          "isCode": false
        },
        {
          "label": "C(m, y-1)",
          "isCode": false
        },
        {
          "label": "C(m, x-1)",
          "isCode": false
        },
        {
          "label": "C(m, x+1)",
          "isCode": false
        }
      ],
      "correctIndex": 0,
      "explanation": "There is a 1-to-1 mapping from bad suffixes to choosing y+1 positions for ')'. Hence C(m, y+1).",
      "wrongExplanations": {
        "1": "This undercounts; the violation corresponds to an extra early ')'.",
        "2": "This mixes '(' counts rather than ')'.",
        "3": "This adds an extra '(', not the extra ')'."
      },
      "hint": "Think of the first place where the balance becomes negative.",
      "isCodeBuilding": false,
      "codeSnippet": null,
      "codeLabel": null
    },
    {
      "id": "q11",
      "phase": "Building the Idea",
      "questionText": "What formula gives the number of valid suffixes that never go below 0?",
      "diagram": null,
      "options": [
        {
          "label": "C(m, y) - C(m, y+1)",
          "isCode": false
        },
        {
          "label": "C(m, y) + C(m, y+1)",
          "isCode": false
        },
        {
          "label": "C(m, x) - C(m, x-1)",
          "isCode": false
        },
        {
          "label": "C(m, x) - C(m, y-1)",
          "isCode": false
        }
      ],
      "correctIndex": 0,
      "explanation": "Total − bad = C(m, y) − C(m, y+1). This matches small checks and the earlier mapping.",
      "wrongExplanations": {
        "1": "Adding counts overcounts; bad should be subtracted.",
        "2": "This is the special case when b=0; here we need y-terms for general b.",
        "3": "This mixes parameters inconsistently."
      },
      "hint": "Subtract the number of bad suffixes from the unconstrained total.",
      "isCodeBuilding": false,
      "codeSnippet": null,
      "codeLabel": null
    },
    {
      "id": "q12",
      "phase": "Building the Idea",
      "questionText": "Check the special case b=0, m=4. Compute C(4,2) − C(4,3).",
      "diagram": null,
      "options": [
        {
          "label": "2",
          "isCode": false
        },
        {
          "label": "3",
          "isCode": false
        },
        {
          "label": "4",
          "isCode": false
        },
        {
          "label": "1",
          "isCode": false
        }
      ],
      "correctIndex": 0,
      "explanation": "C(4,2)=6 and C(4,3)=4, so difference is 2.",
      "wrongExplanations": {
        "1": "6−4 is not 3.",
        "2": "That's the total without subtraction.",
        "3": "6−4 is not 1."
      },
      "hint": "Recall C(4,2)=6 and C(4,3)=4.",
      "isCodeBuilding": false,
      "codeSnippet": null,
      "codeLabel": null
    },
    {
      "id": "q13",
      "phase": "Building the Idea",
      "questionText": "Before applying the formula, which conditions must hold to have a valid completion?",
      "diagram": null,
      "options": [
        {
          "label": "Prefix never negative, (m + b) is even, and m ≥ b",
          "isCode": false
        },
        {
          "label": "Prefix never negative and (m − b) is odd",
          "isCode": false
        },
        {
          "label": "Only m ≥ b",
          "isCode": false
        },
        {
          "label": "Only (m + b) is even",
          "isCode": false
        }
      ],
      "correctIndex": 0,
      "explanation": "We need a nonnegative prefix, integer x,y (so (m+b) even), and enough steps to close (m≥b).",
      "wrongExplanations": {
        "1": "Parity must make x,y integers; odd parity fails.",
        "2": "Parity and prefix validity are also required.",
        "3": "m≥b and prefix validity are also required."
      },
      "hint": "Combine earlier findings about prefix validity and x,y existence.",
      "isCodeBuilding": false,
      "codeSnippet": null,
      "codeLabel": null
    },
    {
      "id": "q14",
      "phase": "Building the Idea",
      "questionText": "For the example n=6 and s=\"(()\", compute y for the suffix.",
      "diagram": "k=3, b=1, m=3, y=(m+b)/2",
      "options": [
        {
          "label": "y = 2",
          "isCode": false
        },
        {
          "label": "y = 1",
          "isCode": false
        },
        {
          "label": "y = 3",
          "isCode": false
        },
        {
          "label": "y = 0",
          "isCode": false
        }
      ],
      "correctIndex": 0,
      "explanation": "m=3 and b=1 ⇒ y=(3+1)/2=2.",
      "wrongExplanations": {
        "1": "That's x, not y.",
        "2": "This would imply x<0.",
        "3": "This ignores the needed closes to finish."
      },
      "hint": "Compute (3+1)/2.",
      "isCodeBuilding": false,
      "codeSnippet": null,
      "codeLabel": null
    },
    {
      "id": "q15",
      "phase": "Writing the Code",
      "questionText": "Choose the input setup and main wrapper.",
      "diagram": null,
      "options": [
        {
          "label": "import sys\nMOD = 10**9 + 7\n\ndef main():\n    data = sys.stdin.read().splitlines()\n    n = int(data[0].strip())\n    s = data[1].strip()",
          "isCode": true
        },
        {
          "label": "MOD = 10**9 + 7\n\ndef main():\n    n = int(input())\n    s = input()",
          "isCode": true
        },
        {
          "label": "import sys\nMOD = 10**9 + 7\n\ndef main():\n    n, s = map(str, sys.stdin.read().split())\n    n = int(n)",
          "isCode": true
        },
        {
          "label": "import sys\nMOD = 10**9 + 7\n\ndef main():\n    data = sys.stdin.readline()\n    n = int(data)\n    s = sys.stdin.readline()",
          "isCode": true
        }
      ],
      "correctIndex": 0,
      "explanation": "Reading both lines via splitlines and stripping is robust and matches the input format.",
      "wrongExplanations": {
        "1": "This can work, but may leave trailing newlines in s depending on environment; we'll keep consistent stripping.",
        "2": "Splitting by whitespace risks merging lines if s contains spaces (or empty lines).",
        "3": "s may include a trailing newline; no strip used."
      },
      "hint": "We need two lines: an integer and a raw string of '(' and ')'.",
      "isCodeBuilding": true,
      "codeSnippet": "import sys\nMOD = 10**9 + 7\n\ndef main():\n    data = sys.stdin.read().splitlines()\n    n = int(data[0].strip())\n    s = data[1].strip()",
      "codeLabel": "Input and main header"
    },
    {
      "id": "q16",
      "phase": "Writing the Code",
      "questionText": "Compute the prefix balance and track the minimum balance.",
      "diagram": null,
      "options": [
        {
          "label": "    k = len(s)\n    bal = 0\n    min_bal = 0\n    for ch in s:\n        if ch == '(': \n            bal += 1\n        else:\n            bal -= 1\n        if bal < min_bal:\n            min_bal = bal",
          "isCode": true
        },
        {
          "label": "    k = len(s)\n    bal = 0\n    min_bal = 0\n    for ch in s:\n        if ch == ')':\n            bal += 1\n        else:\n            bal -= 1\n    min_bal = min(min_bal, bal)",
          "isCode": true
        },
        {
          "label": "    bal = s.count('(') - s.count(')')\n    min_bal = 0\n    k = len(s)",
          "isCode": true
        },
        {
          "label": "    k = len(s)\n    bal = 0\n    min_bal = 0\n    for ch in s:\n        if ch == '(':\n            bal += 1\n        else:\n            bal -= 1\n    # don't track min_bal",
          "isCode": true
        }
      ],
      "correctIndex": 0,
      "explanation": "We must update balance per character and track the minimum balance over all prefixes.",
      "wrongExplanations": {
        "1": "Updates balance with reversed signs and doesn't track prefix minimum correctly.",
        "2": "Net balance alone isn't enough; we need to detect early negatives.",
        "3": "Missing min tracking misses invalid prefixes."
      },
      "hint": "We need both final balance and the lowest prefix balance.",
      "isCodeBuilding": true,
      "codeSnippet": "    k = len(s)\n    bal = 0\n    min_bal = 0\n    for ch in s:\n        if ch == '(': \n            bal += 1\n        else:\n            bal -= 1\n        if bal < min_bal:\n            min_bal = bal",
      "codeLabel": "Prefix balance"
    },
    {
      "id": "q17",
      "phase": "Writing the Code",
      "questionText": "Add early checks: invalid prefix, remaining length, and parity/magnitude conditions.",
      "diagram": null,
      "options": [
        {
          "label": "    if min_bal < 0 or k > n:\n        print(0)\n        return\n    m = n - k\n    if (m + bal) % 2 != 0 or m < bal:\n        print(0)\n        return",
          "isCode": true
        },
        {
          "label": "    if min_bal <= 0:\n        print(0)\n        return\n    m = n - k\n    if (m - bal) % 2 != 0 or m <= bal:\n        print(0)\n        return",
          "isCode": true
        },
        {
          "label": "    if k >= n:\n        print(0)\n        return\n    m = n - k\n    if (m + bal) % 2 == 0 and m >= bal:\n        pass",
          "isCode": true
        },
        {
          "label": "    m = n - k\n    if bal < 0:\n        print(0)\n        return\n    if (m + bal) % 2 == 1 and m > bal:\n        print(0)\n        return",
          "isCode": true
        }
      ],
      "correctIndex": 0,
      "explanation": "Reject if prefix goes negative or k>n. For completion, require (m+bal) even and m≥bal.",
      "wrongExplanations": {
        "1": "min_bal==0 is fine; also wrong parity check and m≤bal rejects valid m=bal cases.",
        "2": "k==n may be valid if balance ends 0; this rejects too much and lacks output path.",
        "3": "Checks bal<0 only, not min over prefix; also parity condition is inverted."
      },
      "hint": "Ensure integer x,y and enough ')' to close b.",
      "isCodeBuilding": true,
      "codeSnippet": "    if min_bal < 0 or k > n:\n        print(0)\n        return\n    m = n - k\n    if (m + bal) % 2 != 0 or m < bal:\n        print(0)\n        return",
      "codeLabel": "Early checks and m"
    },
    {
      "id": "q18",
      "phase": "Writing the Code",
      "questionText": "Compute y, the number of ')' in the suffix.",
      "diagram": null,
      "options": [
        {
          "label": "    y = (m + bal) // 2",
          "isCode": true
        },
        {
          "label": "    y = (m - bal) // 2",
          "isCode": true
        },
        {
          "label": "    y = m - bal",
          "isCode": true
        },
        {
          "label": "    y = bal // 2",
          "isCode": true
        }
      ],
      "correctIndex": 0,
      "explanation": "y = (m + b)/2 by earlier derivation. Integer division is safe after parity check.",
      "wrongExplanations": {
        "1": "That computes x, not y.",
        "2": "This ignores the need to balance '(' and ')'."
      },
      "hint": "We set y=(m+b)/2 earlier.",
      "isCodeBuilding": true,
      "codeSnippet": "    y = (m + bal) // 2",
      "codeLabel": "Compute y"
    },
    {
      "id": "q19",
      "phase": "Writing the Code",
      "questionText": "Precompute factorials and inverse factorials modulo MOD up to m.",
      "diagram": null,
      "options": [
        {
          "label": "    maxn = m\n    fact = [1] * (maxn + 1)\n    for i in range(1, maxn + 1):\n        fact[i] = fact[i-1] * i % MOD\n    invfact = [1] * (maxn + 1)\n    invfact[maxn] = pow(fact[maxn], MOD - 2, MOD)\n    for i in range(maxn, 0, -1):\n        invfact[i-1] = invfact[i] * i % MOD",
          "isCode": true
        },
        {
          "label": "    maxn = n\n    fact = [1] * (maxn + 1)\n    for i in range(maxn):\n        fact[i+1] = fact[i] * i % MOD\n    invfact = [1] * (maxn + 1)\n    invfact[0] = pow(fact[0], MOD - 2, MOD)",
          "isCode": true
        },
        {
          "label": "    maxn = m\n    fact = [1] * (maxn + 1)\n    for i in range(1, maxn + 1):\n        fact[i] = fact[i-1] * i\n    invfact = [1] * (maxn + 1)\n    invfact[maxn] = pow(fact[maxn], MOD - 2)\n    for i in range(maxn):\n        invfact[i] = invfact[i] * (i+1) % MOD",
          "isCode": true
        },
        {
          "label": "    fact = [1] * (m + 1)\n    invfact = [1] * (m + 1)\n    for i in range(1, m + 1):\n        fact[i] = (fact[i-1] * i) % MOD\n        invfact[i] = pow(fact[i], MOD - 2, MOD)",
          "isCode": true
        }
      ],
      "correctIndex": 0,
      "explanation": "We build fact and invfact arrays using a single modular inverse for fact[maxn], then downward fill.",
      "wrongExplanations": {
        "1": "Multiplying by i instead of i+1 is wrong; also invfact[0] is not the right seed.",
        "2": "Missing modulo on fact; pow without MOD arg is slow and wrong type.",
        "3": "Computing inv per i is O(m log MOD) and too slow at 1e6."
      },
      "hint": "Use one modular inverse at the top and a reverse loop for invfact.",
      "isCodeBuilding": true,
      "codeSnippet": "    maxn = m\n    fact = [1] * (maxn + 1)\n    for i in range(1, maxn + 1):\n        fact[i] = fact[i-1] * i % MOD\n    invfact = [1] * (maxn + 1)\n    invfact[maxn] = pow(fact[maxn], MOD - 2, MOD)\n    for i in range(maxn, 0, -1):\n        invfact[i-1] = invfact[i] * i % MOD",
      "codeLabel": "Factorials"
    },
    {
      "id": "q20",
      "phase": "Writing the Code",
      "questionText": "Define a combination function comb(N, K) using the precomputed arrays.",
      "diagram": null,
      "options": [
        {
          "label": "    def comb(N, K):\n        if K < 0 or K > N:\n            return 0\n        return fact[N] * invfact[K] % MOD * invfact[N-K] % MOD",
          "isCode": true
        },
        {
          "label": "    def comb(N, K):\n        if N < 0 or N > K:\n            return 0\n        return fact[N] * invfact[N] % MOD * invfact[K] % MOD",
          "isCode": true
        },
        {
          "label": "    def comb(N, K):\n        if K < 0 or K > N:\n            return 0\n        return fact[N] // (fact[K] * fact[N-K]) % MOD",
          "isCode": true
        },
        {
          "label": "    def comb(N, K):\n        return fact[N] * invfact[K] * invfact[N-K] % MOD",
          "isCode": true
        }
      ],
      "correctIndex": 0,
      "explanation": "Use modular combinatorics with bounds checks: fact[N] * invfact[K] * invfact[N-K] mod MOD.",
      "wrongExplanations": {
        "1": "The bound check is reversed; also uses wrong inv terms.",
        "2": "Integer division doesn't work under modulo; need modular inverses.",
        "3": "Missing bounds check can cause index errors for invalid K."
      },
      "hint": "Remember to handle K<0 or K>N by returning 0.",
      "isCodeBuilding": true,
      "codeSnippet": "    def comb(N, K):\n        if K < 0 or K > N:\n            return 0\n        return fact[N] * invfact[K] % MOD * invfact[N-K] % MOD",
      "codeLabel": "nCk helper"
    },
    {
      "id": "q21",
      "phase": "Writing the Code",
      "questionText": "Compute the final answer using the derived formula and print it.",
      "diagram": null,
      "options": [
        {
          "label": "    ans = (comb(m, y) - comb(m, y + 1)) % MOD\n    print(ans)",
          "isCode": true
        },
        {
          "label": "    ans = comb(m, y) - comb(m, y + 1)\n    print(ans)",
          "isCode": true
        },
        {
          "label": "    ans = (comb(m, y + 1) - comb(m, y)) % MOD\n    print(ans)",
          "isCode": true
        },
        {
          "label": "    ans = (comb(n, y) - comb(n, y + 1)) % MOD\n    print(ans)",
          "isCode": true
        }
      ],
      "correctIndex": 0,
      "explanation": "Use C(m, y) − C(m, y+1) modulo MOD. Keep modulo to avoid negative values.",
      "wrongExplanations": {
        "1": "Could print a negative number; modulo needed.",
        "2": "Order is reversed; would give negative of the desired count.",
        "3": "We must choose from the suffix length m, not n."
      },
      "hint": "Subtract bad from total and apply modulo.",
      "isCodeBuilding": true,
      "codeSnippet": "    ans = (comb(m, y) - comb(m, y + 1)) % MOD\n    print(ans)",
      "codeLabel": "Compute and print"
    },
    {
      "id": "q22",
      "phase": "Writing the Code",
      "questionText": "Add the standard Python entry point to run main().",
      "diagram": null,
      "options": [
        {
          "label": "if __name__ == \"__main__\":\n    main()",
          "isCode": true
        },
        {
          "label": "if __name__ == '__main__':\nmain()",
          "isCode": true
        },
        {
          "label": "if __name__ == '__main__':\n    main",
          "isCode": true
        },
        {
          "label": "main()",
          "isCode": true
        }
      ],
      "correctIndex": 0,
      "explanation": "This properly calls main() when the script is executed.",
      "wrongExplanations": {
        "1": "Incorrect indentation for main() call.",
        "2": "Missing parentheses; this doesn't call the function."
      },
      "hint": "Use the common Python pattern for script entry.",
      "isCodeBuilding": true,
      "codeSnippet": "if __name__ == \"__main__\":\n    main()",
      "codeLabel": "Entry point"
    },
    {
      "id": "q23",
      "phase": "Verifying the Solution",
      "questionText": "Run the code mentally for input:\n6\n(()\nWhat is the output?",
      "diagram": "b=1, m=3, y=(3+1)/2=2 ⇒ C(3,2)−C(3,3)=3−1=2",
      "options": [
        {
          "label": "2",
          "isCode": false
        },
        {
          "label": "1",
          "isCode": false
        },
        {
          "label": "3",
          "isCode": false
        },
        {
          "label": "0",
          "isCode": false
        }
      ],
      "correctIndex": 0,
      "explanation": "We get 3 unconstrained and 1 bad, so 2 valid completions.",
      "wrongExplanations": {
        "1": "That's the count for m=1,b=1, not here.",
        "3": "Prefix is valid and can be completed."
      },
      "hint": "Compute y, then two binomials.",
      "isCodeBuilding": false,
      "codeSnippet": null,
      "codeLabel": null
    },
    {
      "id": "q24",
      "phase": "Verifying the Solution",
      "questionText": "For n=4 and s=\"()(\": what does the code print?",
      "diagram": "b=1, m=1, y=(1+1)/2=1 ⇒ C(1,1)−C(1,2)=1−0=1",
      "options": [
        {
          "label": "1",
          "isCode": false
        },
        {
          "label": "0",
          "isCode": false
        },
        {
          "label": "2",
          "isCode": false
        },
        {
          "label": "3",
          "isCode": false
        }
      ],
      "correctIndex": 0,
      "explanation": "Only one way: a single ')' to close.",
      "wrongExplanations": {
        "1": "There is enough remaining length to place one ')'.",
        "2": "There is only one position."
      },
      "hint": "m=1 and b=1 forces exactly one ')'.",
      "isCodeBuilding": false,
      "codeSnippet": null,
      "codeLabel": null
    },
    {
      "id": "q25",
      "phase": "Verifying the Solution",
      "questionText": "For n=5 and s=\"))(\", what is the output?",
      "diagram": "First char makes balance −1 ⇒ invalid prefix.",
      "options": [
        {
          "label": "0",
          "isCode": false
        },
        {
          "label": "1",
          "isCode": false
        },
        {
          "label": "Depends on parity",
          "isCode": false
        },
        {
          "label": "C(2,1)",
          "isCode": false
        }
      ],
      "correctIndex": 0,
      "explanation": "The prefix goes negative, so no completion is allowed.",
      "wrongExplanations": {
        "2": "Parity is irrelevant once the prefix is invalid.",
        "3": "We don't count combinations for invalid prefixes."
      },
      "hint": "Check min prefix balance first.",
      "isCodeBuilding": false,
      "codeSnippet": null,
      "codeLabel": null
    },
    {
      "id": "q26",
      "phase": "Analyzing Complexity",
      "questionText": "What is the time complexity of the implementation, in terms of n?",
      "diagram": null,
      "options": [
        {
          "label": "O(n) due to factorial precomputation and prefix scan",
          "isCode": false
        },
        {
          "label": "O(log n) due to modular exponentiation",
          "isCode": false
        },
        {
          "label": "O(n^2) due to nested loops",
          "isCode": false
        },
        {
          "label": "O(1) because we compute two combinations only",
          "isCode": false
        }
      ],
      "correctIndex": 0,
      "explanation": "We scan the prefix and build factorials up to m (≤ n), both linear work.",
      "wrongExplanations": {
        "1": "We use a single modular exponentiation, but loops dominate.",
        "3": "Precomputation over m controls complexity."
      },
      "hint": "Count iterations of the loops.",
      "isCodeBuilding": false,
      "codeSnippet": null,
      "codeLabel": null
    },
    {
      "id": "q27",
      "phase": "Analyzing Complexity",
      "questionText": "What is the auxiliary space complexity?",
      "diagram": null,
      "options": [
        {
          "label": "O(n) for the factorial and inverse factorial arrays",
          "isCode": false
        },
        {
          "label": "O(1)",
          "isCode": false
        },
        {
          "label": "O(n^2)",
          "isCode": false
        },
        {
          "label": "O(log n)",
          "isCode": false
        }
      ],
      "correctIndex": 0,
      "explanation": "We store two arrays of length m+1 (≤ n+1).",
      "wrongExplanations": {
        "1": "The arrays grow with input size.",
        "2": "No quadratic structures are used."
      },
      "hint": "How many items do fact and invfact store?",
      "isCodeBuilding": false,
      "codeSnippet": null,
      "codeLabel": null
    },
    {
      "id": "q28",
      "phase": "Analyzing Complexity",
      "questionText": "What should the code output when k == n (prefix length equals n)?",
      "diagram": null,
      "options": [
        {
          "label": "1 if the prefix never goes negative and ends at balance 0; otherwise 0",
          "isCode": false
        },
        {
          "label": "Always 0 because no room to add brackets",
          "isCode": false
        },
        {
          "label": "Always 1 because the prefix is the full sequence",
          "isCode": false
        },
        {
          "label": "Depends only on parity of n",
          "isCode": false
        }
      ],
      "correctIndex": 0,
      "explanation": "With no suffix, the prefix must itself be a valid complete sequence to count as 1.",
      "wrongExplanations": {
        "1": "If the prefix is already valid and complete, it counts.",
        "2": "Invalid prefixes should not be counted.",
        "3": "Parity alone can't validate a sequence."
      },
      "hint": "There are 0 remaining positions, so the prefix must be a full valid sequence.",
      "isCodeBuilding": false,
      "codeSnippet": null,
      "codeLabel": null
    }
  ],
  "finalCodeSnippets": [
    "import sys\nMOD = 10**9 + 7\n\ndef main():\n    data = sys.stdin.read().splitlines()\n    n = int(data[0].strip())\n    s = data[1].strip()",
    "    k = len(s)\n    bal = 0\n    min_bal = 0\n    for ch in s:\n        if ch == '(': \n            bal += 1\n        else:\n            bal -= 1\n        if bal < min_bal:\n            min_bal = bal",
    "    if min_bal < 0 or k > n:\n        print(0)\n        return\n    m = n - k\n    if (m + bal) % 2 != 0 or m < bal:\n        print(0)\n        return",
    "    y = (m + bal) // 2",
    "    maxn = m\n    fact = [1] * (maxn + 1)\n    for i in range(1, maxn + 1):\n        fact[i] = fact[i-1] * i % MOD\n    invfact = [1] * (maxn + 1)\n    invfact[maxn] = pow(fact[maxn], MOD - 2, MOD)\n    for i in range(maxn, 0, -1):\n        invfact[i-1] = invfact[i] * i % MOD",
    "    def comb(N, K):\n        if K < 0 or K > N:\n            return 0\n        return fact[N] * invfact[K] % MOD * invfact[N-K] % MOD",
    "    ans = (comb(m, y) - comb(m, y + 1)) % MOD\n    print(ans)",
    "if __name__ == \"__main__\":\n    main()"
  ],
  "reasoningChain": [
    {
      "question": "What must be true about the given prefix to be extendable?",
      "insight": "No prefix can have negative balance; track running balance and its minimum."
    },
    {
      "question": "How many '(' and ')' must the suffix contain?",
      "insight": "Given remaining length m and current balance b, the suffix has x=(m−b)/2 '(' and y=(m+b)/2 ')' if parity allows and m≥b."
    },
    {
      "question": "How many suffixes exist without the nonnegativity rule?",
      "insight": "Choose positions of ')' among m: C(m, y)."
    },
    {
      "question": "How to enforce never going below 0?",
      "insight": "Subtract the count of \"bad\" suffixes, which equals C(m, y+1), yielding C(m, y) − C(m, y+1)."
    },
    {
      "question": "How to compute combinations efficiently for large n?",
      "insight": "Precompute factorials and inverse factorials modulo 1e9+7 to evaluate C(n, k) in O(1)."
    },
    {
      "question": "What checks and edge cases are needed?",
      "insight": "Reject invalid prefix, ensure (m+b) even and m≥b; when k==n, accept iff prefix ends at balance 0."
    }
  ],
  "_meta": {
    "input_tokens": 1293,
    "output_tokens": 19121,
    "input_cost": 0.001616,
    "output_cost": 0.19121,
    "total_cost": 0.192826
  }
}